LICENSE
MANIFEST.in
README.md
setup.py
site.cfg.default
docs/_config.yml
docs/colors.py
docs/dox.config
docs/example_list.md
docs/index.md
docs/mybib.bib
docs/site_setup.sh
docs/techref-blx.bib
docs/techref.bbl
docs/techref.blg
docs/techref.pdf
docs/techref.tex
docs/.sass-cache/c30965ccb96f1a47390ad25e4a59a590a0c852a6/_default_colors.scssc
docs/.sass-cache/c30965ccb96f1a47390ad25e4a59a590a0c852a6/jekyll-theme-hacker.scssc
docs/.sass-cache/c30965ccb96f1a47390ad25e4a59a590a0c852a6/rouge-base16-dark.scssc
docs/_layouts/default.html
docs/documentation/README_8md.html
docs/documentation/analysis_2____init_____8py.html
docs/documentation/annotated.html
docs/documentation/arrowdown.png
docs/documentation/arrowright.png
docs/documentation/bc_s.png
docs/documentation/bdwn.png
docs/documentation/classes.html
docs/documentation/classpawpyseed_1_1analysis_1_1corrections_1_1DelocalizedStatePerturbationCorrection-members.html
docs/documentation/classpawpyseed_1_1analysis_1_1corrections_1_1DelocalizedStatePerturbationCorrection.html
docs/documentation/classpawpyseed_1_1analysis_1_1corrections_1_1DelocalizedStatePerturbationCorrection__coll__graph.map
docs/documentation/classpawpyseed_1_1analysis_1_1corrections_1_1DelocalizedStatePerturbationCorrection__coll__graph.md5
docs/documentation/classpawpyseed_1_1analysis_1_1corrections_1_1DelocalizedStatePerturbationCorrection__coll__graph.png
docs/documentation/classpawpyseed_1_1analysis_1_1corrections_1_1DelocalizedStatePerturbationCorrection__inherit__graph.map
docs/documentation/classpawpyseed_1_1analysis_1_1corrections_1_1DelocalizedStatePerturbationCorrection__inherit__graph.md5
docs/documentation/classpawpyseed_1_1analysis_1_1corrections_1_1DelocalizedStatePerturbationCorrection__inherit__graph.png
docs/documentation/classpawpyseed_1_1analysis_1_1corrections_1_1PerturbationCorrection-members.html
docs/documentation/classpawpyseed_1_1analysis_1_1corrections_1_1PerturbationCorrection.html
pawpyseed.egg-info/PKG-INFO
pawpyseed.egg-info/SOURCES.txt
pawpyseed.egg-info/dependency_links.txt
pawpyseed.egg-info/not-zip-safe
pawpyseed.egg-info/requires.txt
pawpyseed.egg-info/top_level.txt
