Metadata-Version: 2.1
Name: pawpyseed
Version: 0.7.1
Summary: Parallel C/Python package for numerical analysis of PAW DFT wavefunctions
Home-page: https://github.com/kylebystrom/pawpyseed
Author: Kyle Bystrom
Author-email: kylebystrom@gmail.com
Maintainer: Kyle Bystrom
Maintainer-email: kylebystrom@gmail.com
License: BSD
Platform: UNKNOWN
Classifier: Programming Language :: Python :: 3
Classifier: License :: OSI Approved :: BSD License
Requires-Python: >=3.6
License-File: LICENSE
